odoo/addons/stock_picking_report_product_sticker/README.rst
odoo/addons/stock_picking_report_product_sticker/__init__.py
odoo/addons/stock_picking_report_product_sticker/__manifest__.py
odoo/addons/stock_picking_report_product_sticker/data/menus.xml
odoo/addons/stock_picking_report_product_sticker/i18n/es.po
odoo/addons/stock_picking_report_product_sticker/i18n/it.po
odoo/addons/stock_picking_report_product_sticker/i18n/stock_picking_report_product_sticker.pot
odoo/addons/stock_picking_report_product_sticker/models/__init__.py
odoo/addons/stock_picking_report_product_sticker/models/stock_picking.py
odoo/addons/stock_picking_report_product_sticker/models/stock_picking_type.py
odoo/addons/stock_picking_report_product_sticker/readme/CONTRIBUTORS.md
odoo/addons/stock_picking_report_product_sticker/readme/DESCRIPTION.md
odoo/addons/stock_picking_report_product_sticker/readme/INSTALL.md
odoo/addons/stock_picking_report_product_sticker/readme/USAGE.md
odoo/addons/stock_picking_report_product_sticker/report/report_deliveryslip.xml
odoo/addons/stock_picking_report_product_sticker/static/description/icon.png
odoo/addons/stock_picking_report_product_sticker/static/description/index.html
odoo/addons/stock_picking_report_product_sticker/tests/__init__.py
odoo/addons/stock_picking_report_product_sticker/tests/common.py
odoo/addons/stock_picking_report_product_sticker/tests/test_stock_picking.py
odoo/addons/stock_picking_report_product_sticker/views/stock_picking_type_views.xml
odoo/addons/stock_picking_report_product_sticker/views/stock_picking_views.xml
odoo_addon_stock_picking_report_product_sticker-18.0.1.0.1.dist-info/METADATA
odoo_addon_stock_picking_report_product_sticker-18.0.1.0.1.dist-info/WHEEL
odoo_addon_stock_picking_report_product_sticker-18.0.1.0.1.dist-info/top_level.txt
odoo_addon_stock_picking_report_product_sticker-18.0.1.0.1.dist-info/RECORD
