Metadata-Version: 2.1
Name: odoo-addon-stock_picking_report_product_sticker
Version: 18.0.1.0.1
Requires-Python: >=3.10
Requires-Dist: odoo-addon-product_sticker==18.0.*
Requires-Dist: odoo==18.0.*
Summary: Stock Picking Report - Product Sticker
Home-page: https://github.com/OCA/stock-logistics-reporting
License: AGPL-3
Author: Moduon, Odoo Community Association (OCA)
Author-email: support@odoo-community.org
Classifier: Programming Language :: Python
Classifier: Framework :: Odoo
Classifier: Framework :: Odoo :: 18.0
Classifier: License :: OSI Approved :: GNU Affero General Public License v3
